annovar_tools-0.0.2.data/scripts/annovar_tools.py
process_annovar/__init__.py
process_annovar/split.py
process_annovar/vcf.py
annovar_tools-0.0.2.dist-info/METADATA
annovar_tools-0.0.2.dist-info/WHEEL
annovar_tools-0.0.2.dist-info/top_level.txt
annovar_tools-0.0.2.dist-info/RECORD
