Metadata-Version: 2.1
Name: annovar-tools
Version: 0.0.2
Summary: tools for ANNOVAR
Home-page: UNKNOWN
Author: Ying Zhu
Author-email: win19890412@163.com
License: UNKNOWN
Platform: UNKNOWN
Classifier: Programming Language :: Python :: 3
Classifier: License :: OSI Approved :: MIT License
Classifier: Operating System :: OS Independent
Requires-Dist: pysam
